src/__init__.py
src/pambas.py
pambas-0.1.dist-info/METADATA
pambas-0.1.dist-info/WHEEL
pambas-0.1.dist-info/top_level.txt
pambas-0.1.dist-info/RECORD
