Metadata-Version: 2.1
Name: pambas
Version: 0.1
Requires-Dist: pyperclip
Requires-Dist: g4f
